monitor/__init__.py
monitor/main.py
monitor/version.py
jaaql_monitor-1.6.2.dist-info/LICENSE.txt
jaaql_monitor-1.6.2.dist-info/METADATA
jaaql_monitor-1.6.2.dist-info/WHEEL
jaaql_monitor-1.6.2.dist-info/top_level.txt
jaaql_monitor-1.6.2.dist-info/RECORD
