Metadata-Version: 2.1
Name: jaaql-monitor
Version: 1.6.2
Summary: How to interact with jaaql
Home-page: https://github.com/JAAQL/JAAQL-monitor
Author: Software Quality Measurement and Improvement bv
Author-email: aaron.tasker@sqmi.nl
License: Mozilla Public License Version 2.0 with Commons Clause
License-File: LICENSE.txt
Requires-Dist: requests ~=2.31.0
